LICENSE
README.md
setup.py
missionpanel/__init__.py
missionpanel.egg-info/PKG-INFO
missionpanel.egg-info/SOURCES.txt
missionpanel.egg-info/dependency_links.txt
missionpanel.egg-info/requires.txt
missionpanel.egg-info/top_level.txt
missionpanel/example/__init__.py
missionpanel/example/rsshub.py
missionpanel/example/subprocess.py
missionpanel/example/ttrss.py
missionpanel/handler/__init__.py
missionpanel/handler/handler.py
missionpanel/handler/parallal_handler.py
missionpanel/orm/__init__.py
missionpanel/orm/core.py
missionpanel/orm/handler.py
missionpanel/submitter/__init__.py
missionpanel/submitter/abc.py
missionpanel/submitter/asynchronous.py
missionpanel/submitter/submitter.py