Metadata-Version: 2.1
Name: missionpanel
Version: 1.5.4
Summary: A mission panel
Home-page: https://github.com/yindaheng98/missionpanel
Author: yindaheng98
Author-email: yindaheng98@gmail.com
License: UNKNOWN
Platform: UNKNOWN
Classifier: Programming Language :: Python :: 3
Classifier: License :: OSI Approved :: MIT License
Classifier: Operating System :: OS Independent
License-File: LICENSE
